simple_othello/__init__.py
simple_othello/agent.py
simple_othello/config.py
simple_othello/env.py
simple_othello/humanPlayer.py
simple_othello/main.py
simple_othello/othello.py
simple_othello/randomPlayer.py
simple_othello-1.2.7.dist-info/LICENSE
simple_othello-1.2.7.dist-info/METADATA
simple_othello-1.2.7.dist-info/WHEEL
simple_othello-1.2.7.dist-info/top_level.txt
simple_othello-1.2.7.dist-info/RECORD
