Metadata-Version: 2.1
Name: simple-othello
Version: 1.2.7
Summary: simple_othello
Author: Michiyasu Uchiyama
License: MIT
Keywords: simple_othello othello reversi
Classifier: License :: OSI Approved :: MIT License
Classifier: Programming Language :: Python :: 3.7
License-File: LICENSE
